BCSFE_KR/__init__.py
BCSFE_KR/__main__.py
BCSFE_KR/adb_handler.py
BCSFE_KR/config_manager.py
BCSFE_KR/csv_handler.py
BCSFE_KR/feature_handler.py
BCSFE_KR/game_data_getter.py
BCSFE_KR/helper.py
BCSFE_KR/item.py
BCSFE_KR/managed_item.py
BCSFE_KR/parse_save.py
BCSFE_KR/patcher.py
BCSFE_KR/py.typed
BCSFE_KR/root_handler.py
BCSFE_KR/serialise_save.py
BCSFE_KR/server_handler.py
BCSFE_KR/tracker.py
BCSFE_KR/updater.py
BCSFE_KR/user_input_handler.py
BCSFE_KR/edits/__init__.py
BCSFE_KR/edits/basic/__init__.py
BCSFE_KR/edits/basic/basic_items.py
BCSFE_KR/edits/basic/catfruit.py
BCSFE_KR/edits/basic/catseyes.py
BCSFE_KR/edits/basic/talent_orbs.py
BCSFE_KR/edits/cats/__init__.py
BCSFE_KR/edits/cats/cat_helper.py
BCSFE_KR/edits/cats/cat_id_selector.py
BCSFE_KR/edits/cats/chara_drop.py
BCSFE_KR/edits/cats/clear_cat_guide.py
BCSFE_KR/edits/cats/evolve_cats.py
BCSFE_KR/edits/cats/get_remove_cats.py
BCSFE_KR/edits/cats/talents.py
BCSFE_KR/edits/cats/upgrade_blue.py
BCSFE_KR/edits/cats/upgrade_cats.py
BCSFE_KR/edits/gamototo/__init__.py
BCSFE_KR/edits/gamototo/fix_gamatoto.py
BCSFE_KR/edits/gamototo/gamatoto_xp.py
BCSFE_KR/edits/gamototo/helpers.py
BCSFE_KR/edits/gamototo/ototo_cat_cannon.py
BCSFE_KR/edits/levels/__init__.py
BCSFE_KR/edits/levels/aku.py
BCSFE_KR/edits/levels/allow_filibuster_clearing.py
BCSFE_KR/edits/levels/behemoth_culling.py
BCSFE_KR/edits/levels/clear_tutorial.py
BCSFE_KR/edits/levels/enigma_stages.py
BCSFE_KR/edits/levels/event_stages.py
BCSFE_KR/edits/levels/gauntlet.py
BCSFE_KR/edits/levels/itf_timed_scores.py
BCSFE_KR/edits/levels/legend_quest.py
BCSFE_KR/edits/levels/main_story.py
BCSFE_KR/edits/levels/outbreaks.py
BCSFE_KR/edits/levels/story_level_id_selector.py
BCSFE_KR/edits/levels/towers.py
BCSFE_KR/edits/levels/treasures.py
BCSFE_KR/edits/levels/uncanny.py
BCSFE_KR/edits/levels/unlock_aku_realm.py
BCSFE_KR/edits/other/__init__.py
BCSFE_KR/edits/other/cat_shrine.py
BCSFE_KR/edits/other/claim_user_rank_rewards.py
bcsfe_kr-2.7.0.4.dist-info/METADATA
bcsfe_kr-2.7.0.4.dist-info/WHEEL
bcsfe_kr-2.7.0.4.dist-info/top_level.txt
bcsfe_kr-2.7.0.4.dist-info/RECORD
