Metadata-Version: 2.1
Name: bcsfe-kr
Version: 2.7.0.4
Summary: BCSFE_Python korean translated version
Home-page: UNKNOWN
Author: CintagramABP
License: UNKNOWN
Platform: UNKNOWN
Requires-Python: >=3.9
Requires-Dist: colored
Requires-Dist: tk
Requires-Dist: python-dateutil
Requires-Dist: requests
Requires-Dist: pyyaml
Provides-Extra: testing
Requires-Dist: pytest ; extra == 'testing'
Requires-Dist: pytest-cov ; extra == 'testing'
